{
    "sourceFile": ".env",
    "activeCommit": 0,
    "commits": [
        {
            "activePatchIndex": 0,
            "patches": [
                {
                    "date": 1693275516361,
                    "content": "Index: \n===================================================================\n--- \n+++ \n"
                }
            ],
            "date": 1693275516361,
            "name": "Commit-0",
            "content": "# Environment variables declared in this file are automatically made available to Prisma.\n# See the documentation for more detail: https://pris.ly/d/prisma-schema#accessing-environment-variables-from-the-schema\n\n# Prisma supports the native connection string format for PostgreSQL, MySQL, SQLite, SQL Server, MongoDB and CockroachDB.\n# See the documentation for all the connection string options: https://pris.ly/d/connection-strings\n# you have to put \"/test\" at the end of the database url\nDATABASE_URL=\"mongodb+srv://dennis:dennis1224@cluster0.2rkpbfl.mongodb.net/test\"\nNEXTAUTH_SECRET=\"NEXTAUTH_SECRET\"\n\nGITHUB_ID=d0518a91df2c20361745\nGITHUB_SECRET=215f55d4937b9fea2ac144a4f03cb494ae1624b7\n\nGOOGLE_CLIENT_ID=542651123282-t84jkicdksuarluksh2mfvfjlk0ngcek.apps.googleusercontent.com\nGOOGLE_CLIENT_SECRET=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\n\n\nNEXT_PUBLIC_CLOUDINARY_CLOUD_NAME='dens12'\n"
        }
    ]
}